sopel_modules.osd-0.1.2-py3.6-nspkg.pth
sopel_modules/osd/__init__.py
sopel_modules.osd-0.1.2.dist-info/DESCRIPTION.rst
sopel_modules.osd-0.1.2.dist-info/METADATA
sopel_modules.osd-0.1.2.dist-info/RECORD
sopel_modules.osd-0.1.2.dist-info/WHEEL
sopel_modules.osd-0.1.2.dist-info/metadata.json
sopel_modules.osd-0.1.2.dist-info/namespace_packages.txt
sopel_modules.osd-0.1.2.dist-info/top_level.txt
tests/__init__.py
tests/test_osd.py
