Metadata-Version: 2.0
Name: sopel-modules.osd
Version: 0.1.2
Summary: Sopel OSD is a "niche" method of displaying text in a Sopel bot
Home-page: https://github.com/deathbybandaid/Sopel-OSD
Author: Sam Zick
Author-email: sam@deathbybandaid.net
License: Eiffel Forum License, version 2
Platform: UNKNOWN
Requires-Dist: sopel (<7,>=6.0)
